compress_pptx/__init__.py
compress_pptx/__main__.py
compress_pptx/compress_pptx.py
compress_pptx/util.py
compress_pptx-1.3.0.dist-info/licenses/LICENSE.md
compress_pptx-1.3.0.dist-info/WHEEL
compress_pptx-1.3.0.dist-info/entry_points.txt
compress_pptx-1.3.0.dist-info/METADATA
compress_pptx-1.3.0.dist-info/RECORD
