Metadata-Version: 2.4
Name: compress-pptx
Version: 1.3.0
Summary: Compress images in PPTX files
Author: Werner Robitza
Author-email: Werner Robitza <werner.robitza@gmail.com>
License-Expression: MIT
License-File: LICENSE.md
Classifier: Development Status :: 4 - Beta
Classifier: Intended Audience :: Developers
Classifier: Natural Language :: English
Classifier: Programming Language :: Python :: 3
Classifier: Programming Language :: Python :: 3.9
Classifier: Programming Language :: Python :: 3.10
Classifier: Programming Language :: Python :: 3.11
Classifier: Programming Language :: Python :: 3.12
Classifier: Programming Language :: Python :: 3.13
Classifier: Programming Language :: Python :: 3.14
Requires-Dist: tqdm
Requires-Dist: ffmpeg-progress-yield>=0.11.0
Requires-Python: >=3.9
Project-URL: Homepage, https://github.com/slhck/compress-pptx
